popcon/__init__.py
popcon/__main__.py
popcon/popcon.py
popcon/version.py
python_popcon-3.0.3.dist-info/LICENSE
python_popcon-3.0.3.dist-info/METADATA
python_popcon-3.0.3.dist-info/WHEEL
python_popcon-3.0.3.dist-info/entry_points.txt
python_popcon-3.0.3.dist-info/top_level.txt
python_popcon-3.0.3.dist-info/RECORD
