Metadata-Version: 2.1
Name: python-popcon
Version: 3.0.3
Summary: Python interface to Debian's popularity contest database
Home-page: https://github.com/venthur/python-popcon
Author: Bastian Venthur
Author-email: venthur@debian.org
License: GPL2
Keywords: debian,popcon,popularity contest
Platform: UNKNOWN
Requires-Python: >=3.7, <4
License-File: LICENSE
